{
  "data": [
    {
      "id": 1,
      "name": "John Doe",
      "email": " asjfbabfa@gmail.com"
    },
    {
      "id": 2,
      "name": "Jane Doe",
      "email": "dsdlkaj@gmil.com"
    },
    {
      "id": 3,
      "name": "John Smith",
      "email": " jydgdsbabddfa@gmail.com"
    },
    {
      "id": 4,
      "name": "Javid",
      "email": "dnkajbdjb@gmail.com"
    },
    {
      "id": 5,
      "name": "Mark",
      "email": "johnatan@gmail.com"
    },
    {
      "id": 6,
      "name": "Ted",
      "email": "Bonnie@gmail.com"
    },
    {
      "id": 7,
      "name": "Ted",
      "email": "Bonniefvbfuushffee@gmail.com"
    },
    {
      "id": 8,
      "name": "IZabelle",
      "email": "KLied@gmail.com"
    },
    {
      "id": 9,
      "name": "IZabelle",
      "email": "KLied@gmail.com"
    },
    {
      "id": 10,
      "name": "dddfe",
      "email": "ssdKsssLiefefed@gmail.com"
    },
    {
      "id": 11,
      "name": "TEd",
      "email": "Bundy@gmail.com"
    }
  ]
}